djangocms_scrape_google_photos_album/__init__.py
djangocms_scrape_google_photos_album/admin.py
djangocms_scrape_google_photos_album/cms_plugins.py
djangocms_scrape_google_photos_album/models.py
djangocms_scrape_google_photos_album/tests.py
djangocms_scrape_google_photos_album/views.py
djangocms_scrape_google_photos_album/migrations/0001_initial.py
djangocms_scrape_google_photos_album/migrations/0002_auto_20191204_1859.py
djangocms_scrape_google_photos_album/migrations/__init__.py
djangocms_scrape_google_photos_album/templates/djangocms_scrape_google_photos_album/album.html
djangocms_scrape_google_photos_album-0.0.2.dist-info/LICENSE
djangocms_scrape_google_photos_album-0.0.2.dist-info/METADATA
djangocms_scrape_google_photos_album-0.0.2.dist-info/WHEEL
djangocms_scrape_google_photos_album-0.0.2.dist-info/top_level.txt
djangocms_scrape_google_photos_album-0.0.2.dist-info/RECORD
