Metadata-Version: 2.1
Name: djangocms-scrape-google-photos-album
Version: 0.0.2
Summary: django-cms plugin to scrape a Google Photos public album link for photo urls.
Home-page: https://github.com/k-funk/djangocms-scrape-google-photos-album
Author: Kevin Funk
License: GPLv3+
Platform: UNKNOWN
Classifier: Development Status :: 3 - Alpha
Classifier: Environment :: Web Environment
Classifier: Intended Audience :: Developers
Classifier: License :: OSI Approved :: BSD License
Classifier: Operating System :: OS Independent
Classifier: Programming Language :: Python
Classifier: Programming Language :: Python :: 3
Classifier: Programming Language :: Python :: 3.5
Classifier: Framework :: Django
Classifier: Framework :: Django :: 1.11
Classifier: Framework :: Django CMS
Classifier: Framework :: Django CMS :: 3.5
Classifier: Topic :: Internet :: WWW/HTTP
Classifier: Topic :: Internet :: WWW/HTTP :: Dynamic Content
Classifier: Topic :: Software Development
Classifier: Topic :: Software Development :: Libraries
Requires-Dist: Django (>=1.11)
Requires-Dist: django-cms (>=3.5)
Requires-Dist: requests (>=2.0)
